{"versions": {"FOREST": "/Game/Blueprints/Soldiers/RU/BP_Soldier_RU_Crewman.BP_Soldier_RU_Crewman_C", "DESERT": "/Game/Blueprints/Soldiers/RU_Desert/BP_Soldier_RU_Crewman_Desert.BP_Soldier_RU_Crewman_Desert_C", "SNOW": "/Game/Blueprints/Soldiers/RU/BP_Soldier_RU_Crewman.BP_Soldier_RU_Crewman_C"}, "class_names": ["BP_Soldier_RU_Crewman_C", "BP_Soldier_RU_Crewman_Desert_C"], "type": "crewman", "icon": "icons/role/crewman.png", "tags": ["SUPPORT"], "items": ["aks74u_2mags", "mp443", "ak74bayonet", "rdg2smoke", "generic_fielddressing", "mpl50_shovel_rus", "repairtool", "russian_baigish_binoculars"]}