{"name": "Fool's Road Skirmish v2", "gamemode": "Skirmish", "level": "foolsroad", "size": "small", "minimap": "minimaps/foolsroad.png", "minimap_corners": {"min": {"x": -132576.921875, "y": -132576.921875, "z": 0}, "max": {"x": 44805.078125, "y": 44805.078125, "z": 0}}, "commander": false, "fob_radius": {"name": "Small FOB Radius", "exclusion": 30000, "construction": 15000}, "lighting": "Evening", "units": {"adf": ["adf_s_combinedarms"], "baf": ["baf_s_combinedarms"], "caf": ["caf_s_combinedarms"], "imf": ["imf_s_combinedarms"], "pla": ["pla_s_combinedarms"], "rgf": ["rgf_s_combinedarms"], "usa": ["usa_s_combinedarms"], "usmc": ["usmc_s_combinedarms"], "vdv": ["vdv_s_combinedarms"], "tlf": ["tlf_s_combinedarms"], "wpmc": ["wpmc_s_combinedarms"]}, "teams": [{"tickets": 200, "defaultUnit": "baf_s_combinedarms", "units": null}, {"tickets": 200, "defaultUnit": "imf_s_combinedarms", "units": null}], "objective": {"count": 3, "locations": [{"name": "Main", "order": 0, "location": {"x": 28105.0, "y": -73299.0, "z": -1637.0}, "minimap": {"x": 3710.3716949859627, "y": 1368.8106346754462}}, {"name": "Main", "order": 1, "location": {"x": -105582.3125, "y": -106696.3828125, "z": -4320.009765625}, "minimap": {"x": 623.3435185080787, "y": 597.6180672221533}}, {"name": "Verto", "order": 1, "location": {"x": 10290.0, "y": -89020.0, "z": -5205.0}, "minimap": {"x": 3298.9982749095175, "y": 1005.7906213708268}}, {"name": "Hilltop Encampment", "order": 2, "location": {"x": -33108.0, "y": -78867.0, "z": -1745.0}, "minimap": {"x": 2296.877383274515, "y": 1240.2376791331703}}, {"name": "Homestead", "order": 3, "location": {"x": -72682.0, "y": -81906.0, "z": -5241.0}, "minimap": {"x": 1383.0580329458458, "y": 1170.0628925144604}}]}}