{"name": "Kokan AAS v2", "gamemode": "AAS", "level": "kokan", "size": "medium", "minimap": "minimaps/kokan_aas_v1.png", "minimap_corners": {"min": {"x": -107634.9375, "y": -107566.75, "z": 0}, "max": {"x": 142013.671875, "y": 142013.671875, "z": 0}}, "commander": false, "fob_radius": {"name": "Small FOB Radius", "exclusion": 30000, "construction": 15000}, "lighting": "Sunny", "units": {"adf": ["adf_mo_combinedarms"], "baf": ["baf_mo_combinedarms"], "caf": ["caf_mo_combinedarms"], "ins": ["ins_mo_combinedarms"], "mea": ["mea_mo_combinedarms"], "pla": ["pla_mo_combinedarms"], "rgf": ["rgf_mo_combinedarms"], "usa": ["usa_mo_combinedarms"], "usmc": ["usmc_mo_combinedarms"], "vdv": ["vdv_mo_combinedarms"], "tlf": ["tlf_mo_combinedarms"]}, "teams": [{"tickets": 250, "defaultUnit": "rgf_mo_combinedarms", "units": null}, {"tickets": 250, "defaultUnit": "ins_mo_combinedarms", "units": null}], "objective": {"count": 5, "locations": [{"name": "Main", "order": 0, "location": {"x": 68932.4765625, "y": 78722.265625, "z": -24684.376953125}, "minimap": {"x": 2896.9523596009417, "y": 3057.290320561127}}, {"name": "Main", "order": 1, "location": {"x": 47052.73046875, "y": -89415.96875, "z": -24200.767578125}, "minimap": {"x": 2537.9700274967736, "y": 297.88233965417083}}, {"name": "Nova Isle", "order": 1, "location": {"x": 22233.0, "y": 59236.0, "z": -24140.0}, "minimap": {"x": 2130.7511919722665, "y": 2737.4906207273993}}, {"name": "The Nest", "order": 2, "location": {"x": 17864.0, "y": 32573.0, "z": -24662.0}, "minimap": {"x": 2059.068741808408, "y": 2299.9096310827167}}, {"name": "Hyena Road", "order": 3, "location": {"x": 13963.0, "y": -3057.0, "z": -24250.0}, "minimap": {"x": 1995.064796262697, "y": 1715.1663290896904}}, {"name": "District Center", "order": 4, "location": {"x": 12785.0, "y": -40059.0, "z": -24633.0}, "minimap": {"x": 1975.7372782281295, "y": 1107.9063891417263}}, {"name": "Nexus", "order": 5, "location": {"x": 10620.0, "y": -77378.0, "z": -24167.0}, "minimap": {"x": 1940.2159908386232, "y": 495.44398984120033}}]}}