{"name": "Manicouagan Skirmish v1", "gamemode": "Skirmish", "level": "manicouagan", "size": "small", "minimap": "minimaps/manicouagan.png", "minimap_corners": {"min": {"x": -201657.890625, "y": -201674.84375, "z": 0}, "max": {"x": 201523.078125, "y": 201503.078125, "z": 0}}, "commander": false, "fob_radius": {"name": "Small FOB Radius", "exclusion": 30000, "construction": 15000}, "lighting": "Stormy", "units": {"baf": ["baf_s_combinedarms"], "caf": ["caf_s_combinedarms"], "pla": ["pla_s_combinedarms"], "rgf": ["rgf_s_combinedarms"], "usa": ["usa_s_combinedarms"], "usmc": ["usmc_s_combinedarms"], "vdv": ["vdv_s_combinedarms"], "planmc": ["planmc_s_combinedarms"], "plaagf": ["plaagf_s_combinedarms"], "wpmc": ["wpmc_s_combinedarms"]}, "teams": [{"tickets": 200, "defaultUnit": "caf_s_combinedarms", "units": null}, {"tickets": 200, "defaultUnit": "rgf_s_combinedarms", "units": null}], "objective": {"count": 5, "locations": [{"name": "Main", "order": 0, "location": {"x": -112482.96875, "y": 23391.296875, "z": 5683.982421875}, "minimap": {"x": 905.9467294114437, "y": 2286.511393562403}}, {"name": "Main", "order": 1, "location": {"x": 50354.984375, "y": -92774.125, "z": 12806.2578125}, "minimap": {"x": 2560.2516388616123, "y": 1106.353596758441}}, {"name": "Dam Administration", "order": 1, "location": {"x": -55167.9921875, "y": -41149.453125, "z": 4554.263671875}, "minimap": {"x": 1488.2215940407034, "y": 1630.8234263974725}}, {"name": "Power Station", "order": 2, "location": {"x": -33598.765625, "y": -34046.390625, "z": 4805.486328125}, "minimap": {"x": 1707.3478892969201, "y": 1702.9854730311179}}, {"name": "Underground Dam Outlet", "order": 3, "location": {"x": -49037.84375, "y": -69422.3125, "z": 2182.88671875}, "minimap": {"x": 1550.499057378933, "y": 1343.5913491511792}}, {"name": "Dam Maintenance", "order": 4, "location": {"x": -43912.328125, "y": -107671.625, "z": 3313.568359375}, "minimap": {"x": 1602.5702453248546, "y": 955.0056268194559}}, {"name": "Dam Storage", "order": 5, "location": {"x": -6320.1640625, "y": -70872.4375, "z": 5031.841796875}, "minimap": {"x": 1984.4769223125688, "y": 1328.8591138829952}}]}}