{"name": "Mutaha Skirmish v1", "gamemode": "Skirmish", "level": "mutaha", "size": "small", "minimap": "minimaps/mutaha_skirmish_v1.png", "minimap_corners": {"min": {"x": -84000.0, "y": -67000.0, "z": 0}, "max": {"x": 54000.0, "y": 71000.0, "z": 0}}, "commander": false, "fob_radius": {"name": "Small FOB Radius", "exclusion": 30000, "construction": 15000}, "lighting": "MidDay", "units": {"adf": ["adf_s_combinedarms"], "baf": ["baf_s_combinedarms"], "caf": ["caf_s_combinedarms"], "ins": ["ins_s_combinedarms"], "mea": ["mea_s_combinedarms"], "pla": ["pla_s_combinedarms"], "rgf": ["rgf_s_combinedarms"], "usa": ["usa_s_combinedarms"], "usmc": ["usmc_s_combinedarms"], "vdv": ["vdv_s_combinedarms"], "tlf": ["tlf_s_combinedarms"], "wpmc": ["wpmc_s_combinedarms"]}, "teams": [{"tickets": 200, "defaultUnit": "mea_s_combinedarms", "units": null}, {"tickets": 200, "defaultUnit": "ins_s_combinedarms", "units": null}], "objective": {"count": 5, "locations": [{"name": "Main", "order": 0, "location": {"x": -31099.462890625, "y": -49389.015625, "z": 6.978515625}, "minimap": {"x": 1570.1492753623188, "y": 522.7144347826087}}, {"name": "Main", "order": 1, "location": {"x": 28678.1953125, "y": 19057.6015625, "z": 267.66015625}, "minimap": {"x": 3344.4194782608697, "y": 2554.2893913043476}}, {"name": "Baraka Slums", "order": 1, "location": {"x": -38433.14453125, "y": -7226.4453125, "z": -100.1669921875}, "minimap": {"x": 1352.4771014492753, "y": 1774.1484057971015}}, {"name": "Baraka Market", "order": 2, "location": {"x": -35892.16015625, "y": 8236.5859375, "z": 542.5439453125}, "minimap": {"x": 1427.8964637681158, "y": 2233.1091014492754}}, {"name": "Baraka Road Blockade", "order": 3, "location": {"x": -26063.728515625, "y": 6967.796875, "z": 542.5439453125}, "minimap": {"x": 1719.6157101449276, "y": 2195.449971014493}}, {"name": "Baraka Suburbs", "order": 4, "location": {"x": -13965.3125, "y": 9752.796875, "z": 542.5439453125}, "minimap": {"x": 2078.7107246376813, "y": 2278.112}}, {"name": "Arvand Riverview", "order": 5, "location": {"x": -1496.51171875, "y": 17968.1875, "z": -100.1708984375}, "minimap": {"x": 2448.799188405797, "y": 2521.9543188405796}}]}}